ryvencore_qt/__init__.py
ryvencore_qt/py.typed
ryvencore_qt/resources/__init__.py
ryvencore_qt/resources/node_collapse_icon.svg
ryvencore_qt/resources/node_expand_icon.svg
ryvencore_qt/resources/warning.svg
ryvencore_qt/resources/fonts/__init__.py
ryvencore_qt/resources/fonts/asap/Asap-Bold.ttf
ryvencore_qt/resources/fonts/asap/Asap-BoldItalic.ttf
ryvencore_qt/resources/fonts/asap/Asap-Italic.ttf
ryvencore_qt/resources/fonts/asap/Asap-Medium.ttf
ryvencore_qt/resources/fonts/asap/Asap-MediumItalic.ttf
ryvencore_qt/resources/fonts/asap/Asap-Regular.ttf
ryvencore_qt/resources/fonts/asap/Asap-SemiBold.ttf
ryvencore_qt/resources/fonts/asap/Asap-SemiBoldItalic.ttf
ryvencore_qt/resources/fonts/asap/OFL.txt
ryvencore_qt/resources/fonts/asap/__init__.py
ryvencore_qt/resources/fonts/poppins/OFL.txt
ryvencore_qt/resources/fonts/poppins/Poppins-Black.ttf
ryvencore_qt/resources/fonts/poppins/Poppins-BlackItalic.ttf
ryvencore_qt/resources/fonts/poppins/Poppins-Bold.ttf
ryvencore_qt/resources/fonts/poppins/Poppins-BoldItalic.ttf
ryvencore_qt/resources/fonts/poppins/Poppins-ExtraBold.ttf
ryvencore_qt/resources/fonts/poppins/Poppins-ExtraBoldItalic.ttf
ryvencore_qt/resources/fonts/poppins/Poppins-ExtraLight.ttf
ryvencore_qt/resources/fonts/poppins/Poppins-ExtraLightItalic.ttf
ryvencore_qt/resources/fonts/poppins/Poppins-Italic.ttf
ryvencore_qt/resources/fonts/poppins/Poppins-Light.ttf
ryvencore_qt/resources/fonts/poppins/Poppins-LightItalic.ttf
ryvencore_qt/resources/fonts/poppins/Poppins-Medium.ttf
ryvencore_qt/resources/fonts/poppins/Poppins-MediumItalic.ttf
ryvencore_qt/resources/fonts/poppins/Poppins-Regular.ttf
ryvencore_qt/resources/fonts/poppins/Poppins-SemiBold.ttf
ryvencore_qt/resources/fonts/poppins/Poppins-SemiBoldItalic.ttf
ryvencore_qt/resources/fonts/poppins/Poppins-Thin.ttf
ryvencore_qt/resources/fonts/poppins/Poppins-ThinItalic.ttf
ryvencore_qt/resources/fonts/poppins/__init__.py
ryvencore_qt/resources/fonts/source_code_pro/OFL.txt
ryvencore_qt-0.5.0.dist-info/LICENSE
ryvencore_qt-0.5.0.dist-info/METADATA
ryvencore_qt-0.5.0.dist-info/WHEEL
ryvencore_qt-0.5.0.dist-info/top_level.txt
ryvencore_qt-0.5.0.dist-info/RECORD
