Metadata-Version: 2.1
Name: ryvencore-qt
Version: 0.5.0
Summary: Qt frontend for ryvencore; Library for building Visual Node Editors
Home-page: https://github.com/leon-thomm/ryvencore-qt
Author: Leon Thomm
Author-email: l.thomm@mailbox.org
Project-URL: Website, https://ryven.org
Classifier: Programming Language :: Python :: 3
Classifier: License :: OSI Approved :: MIT License
Classifier: Operating System :: OS Independent
Requires-Python: <3.13,>=3.6
License-File: LICENSE
Requires-Dist: ryvencore ==0.5.*
Requires-Dist: QtPy
Requires-Dist: waiting
Requires-Dist: textdistance
